{
    "images": [
        {
            "imgPath": "img/Cayman/IMG_2333.JPG",
            "imgLocation": "Grand Cayman",
            "description": "Plane Ride In",
            "date": "04/13/2016"
        },
        {
            "imgPath": "img/Cayman/IMG_2336.JPG",
            "imgLocation": "Grand Cayman",
            "description": "Our Room",
            "date": "04/13/2016"
        },
        {
            "imgPath": "img/Cayman/IMG_2407.JPG",
            "imgLocation": "Grand Cayman",
            "description": "Plane Ride In",
            "date": "04/13/2016"
        },
        {
            "imgPath": "img/Cayman/IMG_2397.JPG",
            "imgLocation": "Grand Cayman",
            "description": "Plane Ride In",
            "date": "04/13/2016"
        },
        {
            "imgPath": "img/Cayman/IMG_2477.JPG",
            "imgLocation": "Grand Cayman",
            "description": "Plane Ride In",
            "date": "04/13/2016"
        },
        {
            "imgPath": "img/Cayman/IMG_2484.JPG",
            "imgLocation": "Grand Cayman",
            "description": "In Town",
            "date": "04/15/2016"
        },
        {
            "imgPath": "img/Cayman/IMG_2485.JPG",
            "imgLocation": "Grand Cayman",
            "description": "In Town",
            "date": "04/15/2016"
        },
        {
            "imgPath": "img/Cayman/IMG_2537.JPG",
            "imgLocation": "Grand Cayman",
            "description": "Dinner (pig)",
            "date": "04/15/2016"
        },
        {
            "imgPath": "img/Cayman/IMG_2543.JPG",
            "imgLocation": "Grand Cayman",
            "description": "LOL",
            "date": "04/15/2016"
        },
        {
            "imgPath": "img/Cayman/IMG_2526.JPG",
            "imgLocation": "Grand Cayman",
            "description": "Me and Babe: Farwell Party",
            "date": "04/15/2016"
        }
  ]
}